csvdbclass.py
csvdbclass-0.0.2.dist-info/LICENSE
csvdbclass-0.0.2.dist-info/METADATA
csvdbclass-0.0.2.dist-info/WHEEL
csvdbclass-0.0.2.dist-info/top_level.txt
csvdbclass-0.0.2.dist-info/RECORD
