Metadata-Version: 2.1
Name: csvdbclass
Version: 0.0.2
Summary: Python Database Testing Tool
Author: Sandeep Bajamahal
License: UNKNOWN
Platform: UNKNOWN
Classifier: Programming Language :: Python :: 3
Classifier: License :: OSI Approved :: MIT License
Classifier: Operating System :: OS Independent
Requires-Python: >=3.6
License-File: LICENSE
Requires-Dist: pandas
